Workbook
Name Investimento_mensal: Simulador!$D$12
Name Investimento_mes: Simulador!$E$26
Name Patrimonio: Simulador!$D$15
Name Qtd_anos: Simulador!$D$13
Name Rendimento_carteira: Simulador!$D$8
Name Salario: Simulador!$D$7
Name Taxa_mensal: Simulador!$D$14

Sheet Simulador
C2: Simulador de investimento
C6: Configurações
C7: Salario | D7: 5000
C8: Rendimentos Carteira | D8: 0.006
C9: Sugestão de investimento | D9: =Salario*30% -> 1500
C11: Investimento mensal
C12: Quanto Investir por mês? | D12: 500
C13: Por quantos anos? | D13: 10
C14: Taxa de Rendimento mensal? | D14: 0.0108
C15: Patrimonio Acumulado | D15: =FV(D14,D13*12,D12*-1) -> 121728.83
C16: Dividendos Mensais? | D16: =Patrimonio*Rendimento_carteira -> 730.373
C18: Cenários | E18: Dividendo
B19: 2 | C19: 2 anos | D19: =FV($D$14,$B19*12,$D$12*-1) -> 13615.432 | E19: =D19*$D$8 -> 81.692591
B20: 5 | C20: 5 anos | D20: =FV($D$14,$B20*12,$D$12*-1) -> 41902.01 | E20: =D20*$D$8 -> 251.41206
B21: 10 | C21: 10 anos | D21: =FV($D$14,$B21*12,$D$12*-1) -> 121728.83 | E21: =D21*$D$8 -> 730.373
B22: 20 | C22: 20 anos | D22: =FV($D$14,$B22*12,$D$12*-1) -> 563524.5 | E22: =D22*$D$8 -> 3381.147
B23: 30 | C23: 30 anos | D23: =FV($D$14,$B23*12,$D$12*-1) -> 2166952.4 | E23: =D23*$D$8 -> 13001.714
C25: Perfil | E25: Conservador
C26: Valor a ser investido por mês | E26: 500
C28: Tipo de FII | D28: % Sugestão | E28: Valores
C29: Papel | D29: =VLOOKUP($E$25&"-"&C29,Tab_apoio!A:D,4,0) -> 0.3 | E29: =Investimento_mes*$D29 -> 150
C30: Tijolo | D30: =VLOOKUP($E$25&"-"&C30,Tab_apoio!A:D,4,0) -> 0.5 | E30: =Investimento_mes*$D30 -> 250
C31: Hibridos | D31: =VLOOKUP($E$25&"-"&C31,Tab_apoio!A:D,4,0) -> 0.1 | E31: =Investimento_mes*$D31 -> 50
C32: FOF's | D32: =VLOOKUP($E$25&"-"&C32,Tab_apoio!A:D,4,0) -> 0.1 | E32: =Investimento_mes*$D32 -> 50
C33: Desenvolvimento | D33: =VLOOKUP($E$25&"-"&C33,Tab_apoio!A:D,4,0) -> 0 | E33: =Investimento_mes*$D33 -> 0
C34: Hotelarias | D34: =VLOOKUP($E$25&"-"&C34,Tab_apoio!A:D,4,0) -> 0 | E34: =Investimento_mes*$D34 -> 0
E35: =SUM(E29:E34) -> 500

Sheet Tab_apoio
A1: Chave | B1: Perfil | C1: Tipo de FII | D1: % Sugestão
A2: =B2&"-"&C2 -> Agressivo-Papel | B2: Agressivo | C2: Papel | D2: 0.5
A3: =B3&"-"&C3 -> Agressivo-Tijolo | B3: Agressivo | C3: Tijolo | D3: 0.1
A4: =B4&"-"&C4 -> Agressivo-Hibridos | B4: Agressivo | C4: Hibridos | D4: 0.05
A5: =B5&"-"&C5 -> Agressivo-FOF's | B5: Agressivo | C5: FOF's | D5: 0.05
A6: =B6&"-"&C6 -> Agressivo-Desenvolvimento | B6: Agressivo | C6: Desenvolvimento | D6: 0.2
A7: =B7&"-"&C7 -> Agressivo-Hotelarias | B7: Agressivo | C7: Hotelarias | D7: 0.1
A8: =B8&"-"&C8 -> Moderado-Papel | B8: Moderado | C8: Papel | D8: 0.32
A9: =B9&"-"&C9 -> Moderado-Tijolo | B9: Moderado | C9: Tijolo | D9: 0.4
A10: =B10&"-"&C10 -> Moderado-Hibridos | B10: Moderado | C10: Hibridos | D10: 0.08
A11: =B11&"-"&C11 -> Moderado-FOF's | B11: Moderado | C11: FOF's | D11: 0.1
A12: =B12&"-"&C12 -> Moderado-Desenvolvimento | B12: Moderado | C12: Desenvolvimento | D12: 0.1
A13: =B13&"-"&C13 -> Moderado-Hotelarias | B13: Moderado | C13: Hotelarias | D13: 0.1
... A19: =B19&"-"&C19 -> Conservador-Hotelarias | B19: Conservador | C19: Hotelarias | D19: 0
